{
  "accountAssociation": {
    "header": "eyJmaWQiOjExMTkzOTEsInR5cGUiOiJjdXN0b2R5Iiwia2V5IjoiMHgwMjc0RDI2MmE5MjE1MzQ4MmFkQUJlNDc0RTM1QjkwMzU3MGE5NTAzIn0",
    "payload": "eyJkb21haW4iOiJiYXNlLW1pbmktYXBwLWNoaS52ZXJjZWwuYXBwIn0",
    "signature": "MHg5MmNlMzI4YWJkMmEwZjQxM2YwMWNjZTk0ZmM2ZDliZjk2NmNmZDlkNTdjOTEzMzk2YTA3Y2NlYTQ3NjM3NjIwNDJiMjk1N2E2NjAyZjU4MjhmY2EyM2ZmNzZlY2FhNTQzNWExZGYxMzYxNTM2MDE2YTM0ODA2MWMzNWU3ZWY5NzFi"
  },
  "baseBuilder": {
    "allowedAddresses": ["0x6BBf941a7c5e27ee2C61db21B43b577d1b3BC2c5"]
  },
  "frame": {
    "version": "next",
    "name": "Dripshop.live",
    "description": "Collect, trade, and open instant packs of digital trading cards. Build your collection and discover rare finds.",
    "iconUrl": "https://cdn.dripshop.live/images/mini_app_logo.jpg",
    "homeUrl": "https://base-mini-app-chi.vercel.app",
    "ogTitle": "Dripshop Live - Trading Cards",
    "ogDescription": "Collect, trade, and open instant packs of digital trading cards. Build your collection today!",
    "imageUrl": "https://cdn.dripshop.live/images/mini_app_hero.jpg",
    "ogImageUrl": "https://cdn.dripshop.live/images/mini_app_hero.jpg",
    "heroImageUrl": "https://cdn.dripshop.live/images/mini_app_hero.jpg",
    "splashImageUrl": "https://cdn.dripshop.live/images/mini_app_logo.jpg",
    "splashBackgroundColor": "#ffffff",
    "primaryCategory": "shopping",
    "subtitle": "Digital trading card packs",
    "tagline": "Open packs, find rare cards",
    "tags": ["trading", "cards", "collectibles", "packs", "digital"],
    "buttonTitle": "Launch Dripshop.live",
    "noindex": false,
    "screenshotUrls": [
      "https://cdn.dripshop.live/images/mini_app_home.png",
      "https://cdn.dripshop.live/images/mini_app_details.png",
      "https://cdn.dripshop.live/images/mini_app_open.png"
    ]
  }
}
